setup.py
pyforward/__init__.py
pyforward/exceptions.py
pyforward/static.py
pyforward.egg-info/PKG-INFO
pyforward.egg-info/SOURCES.txt
pyforward.egg-info/dependency_links.txt
pyforward.egg-info/not-zip-safe
pyforward.egg-info/top_level.txt
pyforward/models/__init__.py
pyforward/models/mapping.py
pyforward/models/response.py
pyforward/network/__init__.py
pyforward/network/igd.py
pyforward/network/requester.py
pyforward/network/ssdp.py