Metadata-Version: 2.1
Name: pyforward
Version: 0.0.1
Summary: port forwarding by https://github.com/imranmaj/pyforward?tab=readme-ov-file
Author-email: dev.nevermore696@gmail.com
